simple_onvif/__init__.py
simple_onvif/__main__.py
simple_onvif/arguments.py
simple_onvif/entrypoint.py
simple_onvif/logging/__init__.py
simple_onvif/logging/colored_formatter.py
simple_onvif/logging/logging.py
simple_onvif/www/__init__.py
simple_onvif-0.0.1.dist-info/LICENSE
simple_onvif-0.0.1.dist-info/METADATA
simple_onvif-0.0.1.dist-info/WHEEL
simple_onvif-0.0.1.dist-info/entry_points.txt
simple_onvif-0.0.1.dist-info/top_level.txt
simple_onvif-0.0.1.dist-info/RECORD
